Workbook
Name _00_Transfer: [1]JCR!$A$10:$T$3599,[1]JCR!$AQ$10:$AQ$3599
Name _00_Transfer: [2]JCR!$A$10:$T$3599,[2]JCR!$AQ$10:$AQ$3599
Name Printarea: #N/A

Sheet Reporting
C3: =NOTES!D7 -> XXXX CO-OPERATIVE CREDIT UNION LTD.
A7: FINANCIAL & STATISTICAL REPORT FOR THE MONTH OF | E7: =NOTES!F3 -> 44865
A9: 2024 V6.1
A10: 0. MEMBERSHIP INFORMATION | D10: Total | E10: Females | F10: Males | G10: Groups
A11: Active Members: | D11: =SUM(E11:G11) -> 0 | E11: =NOTES!E17 -> 0 | F11: =NOTES!F17 -> 0 | G11: =NOTES!G17 -> 0
A12: Inactive Members: | D12: =SUM(E12:G12) -> 0 | E12: =NOTES!E18 -> 0 | F12: =NOTES!F18 -> 0 | G12: =NOTES!G18 -> 0
A13: Dormant Members: | D13: =SUM(E13:G13) -> 0 | E13: =NOTES!E19 -> 0 | F13: =NOTES!F19 -> 0 | G13: =NOTES!G19 -> 0
A14: Total Membership: | D14: =SUM(E14:G14) -> 0 | E14: =SUM(E11:E13) -> 0 | F14: =SUM(F11:F13) -> 0 | G14: =SUM(G11:G13) -> 0
A15: Number of persons in the group (if available): | D15: =SUM(E15:G15) -> 0 | E15: =NOTES!E21 -> 0 | F15: =NOTES!F21 -> 0
A16: Number of Youth Savers (if applicable): | D16: =SUM(E16:G16) -> 41202436 | E16: =NOTES!E22 -> 41193190 | F16: =NOTES!F22 -> 9246
A17: Number of Mobile Banking Client (if available): | D17: =SUM(E17:G17) -> 0 | E17: =NOTES!E23 -> 0 | F17: =NOTES!F23 -> 0
A19: 1. MEMBERS DEPOSITS AND LOANS | D19: Total | E19: Females | F19: Males | G19: Groups
A20: Amount of Active Shares | D20: =ROUND(SUM(E20:G20),2) -> 0 | E20: =NOTES!E27 -> 0 | F20: =NOTES!F27 -> 0 | G20: =NOTES!G27 -> 0
A21: Amount of Inactive Shares | D21: =ROUND(SUM(E21:G21),2) -> 0 | E21: =NOTES!E28 -> 0 | F21: =NOTES!F28 -> 0 | G21: =NOTES!G28 -> 0
A22: Amount of Dormant Shares | D22: =ROUND(SUM(E22:G22),2) -> 0 | E22: =NOTES!E29 -> 0 | F22: =NOTES!F29 -> 0 | G22: =NOTES!G29 -> 0
A23: Total Amount of Shares: | D23: =SUM(D20:D22) -> 0 | E23: =SUM(E20:E22) -> 0 | F23: =SUM(F20:F22) -> 0 | G23: =SUM(G20:G22) -> 0
A24: Amount of Active Savings | D24: =ROUND(SUM(E24:G24),2) -> 0 | E24: =NOTES!E30 -> 0 | F24: =NOTES!F30 -> 0 | G24: =NOTES!G30 -> 0
A25: Amount of Inactive Savings | D25: =ROUND(SUM(E25:G25),2) -> 0 | E25: =NOTES!E31 -> 0 | F25: =NOTES!F31 -> 0 | G25: =NOTES!G31 -> 0
A26: Amount of Dormant Savings | D26: =ROUND(SUM(E26:G26),2) -> 0 | E26: =NOTES!E32 -> 0 | F26: =NOTES!F32 -> 0 | G26: =NOTES!G32 -> 0
A27: Total Amount of Savings: | D27: =SUM(D24:D26) -> 0 | E27: =SUM(E24:E26) -> 0 | F27: =SUM(F24:F26) -> 0 | G27: =SUM(G24:G26) -> 0
A28: Number of loans disbursed | D28: =ROUND(SUM(E28:G28),2) -> 0 | E28: =NOTES!E34 -> 0 | F28: =NOTES!F34 -> 0 | G28: =NOTES!G34 -> 0
A29: Amount of loans disbursed (Gh¢) | D29: =ROUND(SUM(E29:G29),2) -> 0 | E29: =NOTES!E35 -> 0 | F29: =NOTES!F35 -> 0 | G29: =NOTES!G35 -> 0
A30: Number of Loans Outstanding | D30: =SUM(E30:G30) -> 0 | E30: =NOTES!E36 -> 0 | F30: =NOTES!F36 -> 0 | G30: =NOTES!G36 -> 0
A31: Amount of Loans Outstanding (Gh¢) | D31: =ROUND(SUM(E31:G31),2) -> 0 | E31: =NOTES!E37 -> 0 | F31: =NOTES!F37 -> 0 | G31: =NOTES!G37 -> 0
A32: No. of Delinquent Borrowers (arrears of 30 days and more): | D32: =ROUND(SUM(E32:G32),2) -> 0 | E32: =NOTES!E38 -> 0 | F32: =NOTES!F38 -> 0 | G32: =NOTES!G38 -> 0
A33: Amount of Delinquent Loans (Gh¢) | D33: =ROUND(SUM(E33:G33),2) -> 0 | E33: =NOTES!E39 -> 0 | F33: =NOTES!F39 -> 0 | G33: =NOTES!G39 -> 0
A34: Amount of Youth Savings (GH¢) | D34: =SUM(E34:G34) -> 1.6260082e+08 | E34: =NOTES!E33 -> 41193190 | F34: =NOTES!F33 -> 9246 | G34: =NOTES!G33 -> 1.2139838e+08
A35: Delinquency Rate (%): | D35: =IF(ISERROR(D33/D31),"",(D33/D31)) | E35: =IF(ISERROR(E33/E31),"",(E33/E31)) | F35: =IF(ISERROR(F33/F31),"",(F33/F31)) | G35: =IF(ISERROR(G33/G31),"",(G33/G31))
A36: Standard: | D36: not more than 5%
A38: 2. RECEIPTS AND PAYMENTS | C38: =E7 -> 44865
D39: =IF(B54=F54,"",B54-F54) | E39: =IF(B54=F54,"","difference") | I39: =IF(F41=B82,"",F41-B82)
A40: RECEIPTS | D40: PAYMENTS
A41: Beg. of the month cash | B41: =NOTES!C45 -> 0 | D41: End of the month cash bal | F41: =NOTES!G45 -> 0
A43: Members Shares Dep. | B43: =NOTES!C47 -> 0 | D43: Members Shares With. | F43: =NOTES!G47 -> 0
A44: Members Savings dep. | B44: =NOTES!C48 -> 0 | D44: Members Savings With. | F44: =NOTES!G48 -> 0
A45: Members Loan Repay. | B45: =NOTES!C49 -> 0 | D45: Loans to Members | F45: =NOTES!G49 -> 0
A46: Bank Savings W/D | B46: =NOTES!C50 -> 0 | D46: Bank Savings Dep. | F46: =NOTES!G50 -> 0
A47: Bank Current W/D | B47: =NOTES!C51 -> 0 | D47: Bank Current Dep. | F47: =NOTES!G51 -> 0
A48: CUA/CFF/W/D | B48: =NOTES!C52 -> 0 | D48: CUA/CFF/ Dep. | F48: =NOTES!G52 -> 0
A49: T-Bills Discounted | B49: =NOTES!C53 -> 0 | D49: T-Bills Invested | F49: =NOTES!G53 -> 0
A50: Other Receipts (total) | B50: =NOTES!C54 -> 0 | D50: Other Payments (total) | F50: =NOTES!G54 -> 0
A51: Mobilized Deposit | B51: =NOTES!C56 -> 0 | D51: Mobilizers Withdrawal | F51: =NOTES!G56 -> 0
A52: Income for the month | B52: =C64 -> 0 | D52: Expenses for the month | F52: =C75 -> 0
A53: (see 3. income and expenses below) | D53: (see 3. income and expenses below)
A54: Test sum | B54: =ROUND(SUM(B41:B53),2) -> 0 | C54: =IF(B54=F54,"ok","error!") -> ok | D54: Test sum | F54: =ROUND(SUM(F41:F53),2) -> 0 | G54: =ROUND(SUM(G41:G53),2) -> 0
A56: 3.COMPREHENSIVE INCOME STATEMENT ( INCOME AND EXPENSES) AS AT | F56: =E7 -> 44865
A58: INCOME | C58: =E7 -> 44865 | E58: YEAR TO DATE
A59: 41 Interest on Loans | C59: =NOTES!E74 -> 0 | E59: =NOTES!G74 -> 0
A60: 42 Interest on Liquid Investments | C60: =NOTES!E81 -> 0 | E60: =NOTES!G81 -> 0
A61: 45 Other Financial Income | C61: =NOTES!E88 -> 0 | E61: =NOTES!G88 -> 0
A62: 46 Non Financial Income | C62: =NOTES!E101 -> 0 | E62: =NOTES!G101 -> 0
A64: Total Income | C64: =SUM(C59:D63) -> 0 | E64: =SUM(E59:F63) -> 0
A66: EXPENSES | C66: =C58 -> 44865 | E66: YEAR TO DATE
A67: 51 Cost of Funds | C67: =NOTES!E109 -> 0 | E67: =NOTES!G109 -> 0
A68: 52 Personnel Cost | C68: =NOTES!E122 -> 0 | E68: =NOTES!G122 -> 0
A69: 53 Occupancy | C69: =NOTES!E129 -> 0 | E69: =NOTES!G129 -> 0
A70: 54 Organizational | C70: =NOTES!E143 -> 0 | E70: =NOTES!G143 -> 0
A71: 55 Security | C71: =NOTES!E152 -> 0 | E71: =NOTES!G152 -> 0
A72: 56 Administration | C72: =NOTES!E161 -> 0 | E72: =NOTES!G161 -> 0
A73: 57 Provision for Loan Losses and Write Off | C73: =NOTES!E166 -> 0 | E73: =NOTES!G166 -> 0
A75: Total Expenses | C75: =SUM(C67:D73) -> 0 | E75: =SUM(E67:F73) -> 0
A77: Surplus Difference | C77: =C64-C75 -> 0 | E77: =E64-E75 -> 0
A79: 4. STATEMENT OF FINANCIAL POSITION (BALANCE SHEET) AS AT | E79: =E7 -> 44865
A81: ASSETS | D81: LIABILITIES + CAPITAL
A82: 1100 Cash Balance | B82: =NOTES!G178 -> 0 | D82: 21 Current Liabilities | F82: =NOTES!G273 -> 0
A83: 1101 Curr. Bank Balance | B83: =NOTES!G185 -> 0 | D83: 22 Members Savings | F83: =NOTES!G285 -> 0
A84: 12 Liquid Investments | B84: =NOTES!G210 -> 0 | D84: 23 External Loans | F84: =NOTES!G292 -> 0
A85: 13 Other Investments | B85: =NOTES!G219 -> 0 | D85: 31 Members Shares | F85: =NOTES!G298 -> 0
A86: 14 Loans To Members | B86: =NOTES!G233 -> 0 | D86: 32 Reserves (incl. last years netsurplus undistributed) | F86: =NOTES!G305 -> 0
A87: (24 Prov. for Loan Loss) | B87: =-NOTES!G234 -> 0 | C87: neg.!
A88: 15 Other Current Assets | B88: =NOTES!G246 -> 0
A89: 16 Non Current Assets | B89: =NOTES!G257 -> 0
A90: (25 Accum. Depreciation) | B90: =-NOTES!G258 -> 0 | C90: neg.! | D90: 39 Surplus Year To Date | F90: =E77 -> 0 | H90: =IF(E77=F90,"","Surplus Difference "&TEXT(F90-E77,"#,##0.00")&" difference; please check 39 Surplus Year To Date in line 70 and 84!")
D91: (see 3. income and expenses above)
A92: Total Assets | B92: =ROUND(SUM(B82:B91),2) -> 0 | C92: =IF(B92=F92,"ok","error!") -> ok | D92: Total Liabilities + Capital | F92: =ROUND(SUM(F82:F91),2) -> 0 | G92: =ROUND(SUM(G82:G91),2) -> 0
A94: Information on ratios: | D94: =IF(B92=F92,"",B92-F92) | E94: =IF(B92=F92,"","difference")
A96: Liquidity reserve | B96: =IF(ISERROR(SUM(B82:B84)/B92),"",(SUM(B82:B84)/B92)) | C96: =B96 | D96: (Total liquid funds / total assets *100)
A97: Return on assets | B97: =(IF(ISERROR(SUM(E77)/B92),"",(SUM(E77)/B92))) | C97: =B97 | D97: (Surplus difference / total assets *100)
A98: Capital adequacy | B98: =IF(ISERROR(SUM(F85:G87)/B92),"",(SUM(F85:G87,F90)/B92)) | C98: =B98 | D98: ([Member shares + total capital res.] / total assets *100)
A99: Delinquency Rate | B99: =IF(ISERROR(D33/D31),"",(D33/D31)) | C99: =B99 | D99: ([Amount of Delinquent Loans] / Amount of Loans Outstanding*100)
A100: Equity Ratio | B100: =((SUM(F82:G84))/(SUM(F85,F86,F90))) -> #DIV/0! | C100: =(B100)/100 -> #DIV/0! | D100: ([Current Liabilities+Members Savings+External Loans]/[Members Shares+Reserves+Surplus Year To Date])
A102: 5. OTHER INFORMATION
A104: Dates of Committees Meetings (like 1st Sunday, 3rd Sunday, …)
B105: In Place (Yes/No) | D105: Regular Meeting Dates | F105: No. of Meetings in Period
A106: Management Com.: | B106: =NOTES!C316 -> No | D106: =NOTES!E316 -> 1st Sunday | F106: =NOTES!G316 -> 0
A107: Supervisory Com.: | B107: =NOTES!C317 -> No | D107: =NOTES!E317 -> 0 | F107: =NOTES!G317 -> 0
A108: Loans Committee | B108: =NOTES!C318 -> No | D108: =NOTES!E318 -> 0 | F108: =NOTES!G318 -> 0
A109: Education Committee | B109: =NOTES!C319 -> Yes | D109: =NOTES!E319 -> 0 | F109: =NOTES!G319 -> 0
A111: 6. EMPLOYEES INFORMATION
D113: Total | E113: Females | F113: Males
A114: Number of Permanent Employees: | D114: =SUM(E114:F114) -> 0 | E114: =NOTES!G323 -> 0 | F114: =NOTES!H323 -> 0
A115: Number of Temporal Employees: | D115: =SUM(E115:F115) -> 0 | E115: =NOTES!G324 -> 0 | F115: =NOTES!H324 -> 0
A116: Number of Employees covered under CCUPP: | D116: =SUM(E116:F116) -> 0 | E116: =NOTES!G325 -> 0 | F116: =NOTES!H325 -> 0
A117: Total Number of Employees | D117: =SUM(E117:F117) -> 0 | E117: =SUM(E114:E115) -> 0 | F117: =SUM(F114:F115) -> 0
A120: Prepared by: | D120: Approved by: | G120: Reviewed by:
A122: =NOTES!A332 -> Mrs./Mr. | D122: =NOTES!D332 -> Mrs./Mr. | F122: =NOTES!H332 -> Mrs./Mr.
A123: Name:Position / Date | D123: Name:Position / Date | G123: Name:Position / Date
A125: Signature:................................................... | D125: Signature:................................................... | F125: Signature:...................................................
A126: Note: | B126: This Report must be submitted before the 15th of the ensuing month at cudbase.cuagh.com
A127: Distribution:
...

Sheet NOTES
B3: FINANCIAL & STATISTICAL REPORT FOR THE MONTH OF | F3: 44865
C5: Credit Union ID:
B7: Credit Union Name: | D7: XXXX CO-OPERATIVE CREDIT UNION LTD.
B10: Number of Branches | E10: 8
B11: Number of Branches Consolidated in This Report | E11: 5
B12: Number of Branches Not Consolidated in This Report | E12: =E10-E11 -> 3 | F12: Please Explain why this Branches could not Report
B14: 0. MEMBERSHIP INFORMATION
B16: MEMBERS | E16: Females | F16: Males | G16: Groups
B17: Active Members:
B18: Inactive Members:
B19: Dormant Members:
B20: Total Membership: | E20: =SUM(E17:E19) -> 0 | F20: =SUM(F17:F19) -> 0 | G20: =SUM(G17:G19) -> 0
B21: Number of persons in the group Cell G17 (if available): | G21: =E21+F21+E22+F22 -> 41202436
B22: Number of Youth Savers (if applicable): | E22: ='Youth Savings'!E13 -> 41193190 | F22: ='Youth Savings'!E12 -> 9246 | G22: ='Youth Savings'!E14 -> 1.2139838e+08
B23: Number of Mobile Banking Client (if available): | E23: 0 | F23: 0
B25: 1. MEMBERS DEPOSITS AND LOANS
E26: Females | F26: Males | G26: Groups
B27: Amount of Active Shares (GH¢) | E27: 0 | F27: 0 | G27: 0 | H27: =IF((SUM(E27:G29)=G298),"","Total Shares Bal. is "&TEXT(SUM(E27:G29)-G298,"#,##0.00")&" difference compared to Balance Sheet; please check member shares in line 22 and 79!")
B28: Amount of Inactive Shares (GH¢) | E28: 0 | F28: 0 | G28: 0
B29: Amount of Dormant Shares (GH¢) | E29: 0 | F29: 0 | G29: 0
B30: Amount of Active Savings (GH¢) | E30: 0 | F30: 0 | G30: 0 | H30: =IF(SUM(E30:G32,E40:G40)=G285,"","Total Shares Bal. is "&TEXT((SUM(E30:G32,E40:G40))-G285,"#,##0.00")&" difference compared to Balance Sheet; please check member shares in line 22 and 79!")
B31: Amount of Inactive Savings (GH¢) | E31: 0 | F31: 0 | G31: 0
B32: Amount of Dormant Savings (GH¢) | E32: 0 | F32: 0 | G32: 0
B33: Amount of Youth Savings (GH¢) | E33: ='Youth Savings'!E21 -> 41193190 | F33: ='Youth Savings'!E20 -> 9246 | G33: ='Youth Savings'!E22 -> 1.2139838e+08
B34: Number of loans disbursed during the month | E34: 0 | F34: 0 | G34: 0
B35: Amount of loans disbursed during the month (GH¢) | E35: 0 | F35: 0 | G35: 0 | H35: =IF((SUM(E35:G35)=G49),"","Total Amount of Loans Disbursed for the month. is "&TEXT(SUM(E35:G35)-G49,"#,##0.00")&" difference compared to Loans to Members Payment (G45) in Receipt and Payment Report; please check member shares in line 31 and 45!")
B36: Number of Loans Outstanding | E36: 0 | F36: 0 | G36: 0
B37: Amount of Loans Outstanding (GH¢) | E37: 0 | F37: 0 | G37: 0 | H37: =IF((SUM(E37:G37))=G233,"","Total Shares Bal. is "&TEXT((SUM(E37:G37))-G233,"#,##0.00")&" difference compared to Balance Sheet; please check member shares in line 22 and 79!")
B38: No. of Delinquent Borrowers (arrears of 30 days and more): | E38: 0 | F38: 0 | G38: 0
B39: Amount of Delinquent Loans (GH¢) | E39: 0 | F39: 0 | G39: 0
B40: Amount Mobile Banking Client (if available): | E40: 0 | F40: 0 | G40: 0
B42: 2. RECEIPTS AND PAYMENTS | D42: =F3 -> 44865
E43: =IF(C59=G59,"",C59-G59) | F43: =IF(C59=G59,"","difference")
B44: RECEIPTS | F44: PAYMENTS
B45: Beg. of the month cash | C45: 0 | F45: End of the month cash bal | G45: =G178 -> 0
B47: Members Shares Dep. | C47: 0 | F47: Members Shares With. | G47: 0
B48: Members Savings dep. | C48: 0 | F48: Members Savings With. | G48: 0
B49: Members Loan Repay. | C49: 0 | F49: Loans to Members | G49: 0
B50: Bank Savings W/D | C50: 0 | F50: Bank Savings Dep. | G50: 0
B51: Bank Current W/D | C51: 0 | F51: Bank Current Dep. | G51: 0
B52: CUA/CFF/W/D | C52: 0 | F52: CUA/CFF/ Dep. | G52: 0
B53: T-Bills Discounted | C53: 0 | F53: T-Bills Invested | G53: 0
B54: Other Receipts (total) | C54: 0 | F54: Other Payments (total) | G54: 0
B55: Sub- Total for the Month | C55: =SUM(C45,C47:D54) -> 0 | F55: Sub- Total for the Month | G55: =SUM(G45,G47:H54) -> 0
B56: Amount Deposit by Mobile Banking Client for the Month (if available): | F56: Amount Withdrawn by Mobile Banking Client for the Month (if available): | G56: 0
B57: Income for the month | C57: =SUM(E74,E81,E88,E101) -> 0 | F57: Expenses for the month | G57: =SUM(E109,E122,E129,E143,E152,E161,E166) -> 0
B58: (see 3. income and expenses below) | F58: (see 3. income and expenses below)
B59: Test sum | C59: =ROUND(SUM(C55,C56,C57),2) -> 0 | E59: =IF(C59=G59,"ok","error!") -> ok | F59: =B59 -> Test sum | G59: =ROUND(SUM(G55,G56,G57),2) -> 0 | H59: =ROUND(SUM(H45:H58),2) -> 0
B63: NOTES TO THE STATEMENT OF COMPREHENSIVE INCOME FOR | G63: =F3 -> 44865
B65: INCOME
B66: INTEREST ON LOANS | E66: CURRENT MONTH | G66: YEAR TO DATE
B67: Interest On Long Term Loans | E67: 0 | G67: 0
B68: Interest On Short Term Loan | E68: 0 | G68: 0
B69: Interest On Long Term Loans | E69: 0 | G69: 0
B70: Interest On Loans To Members 2 | E70: 0 | G70: 0
B71: Interest On Loans To Members 3 | E71: 0 | G71: 0
B72: Interest On Loans To Members 4 | E72: 0 | G72: 0
B73: Interest On Loans To Members 5 | E73: 0 | G73: 0
B74: TOTAL | E74: =SUM(E67:F73) -> 0 | G74: =SUM(G67:H73) -> 0
B76: INTEREST ON LIQUID INVESTMENTS | E76: CURRENT MONTH | G76: YEAR TO DATE
B77: Interest On Liquid Investments 1 | E77: 0 | G77: 0
B78: Interest On Liquid Investments 2 | E78: 0 | G78: 0
B79: Interest On Liquid Investments 3 | E79: 0 | G79: 0
B80: Interest On Liquid Investments 4 | E80: 0 | G80: 0
B81: TOTAL | E81: =SUM(E77:F80) -> 0 | G81: =SUM(G77:H80) -> 0
B83: OTHER FINANCIAL INCOME | E83: CURRENT MONTH | G83: YEAR TO DATE
B84: Interest On Other Investment 1 | E84: 0 | G84: 0
B85: Interest On Other Investment 2 | E85: 0 | G85: 0
B86: Interest On Other Investment 3 | E86: 0 | G86: 0
B87: Interest On Other Investment 4 | E87: 0 | G87: 0
B88: TOTAL | E88: =SUM(E84:F87) -> 0 | G88: =SUM(G84:H87) -> 0
B90: NON FINANCIAL INCOME | E90: CURRENT MONTH | G90: YEAR TO DATE
B91: Entrance Fee | E91: 0 | G91: 0
B92: Sale Of Membership Form | E92: 0 | G92: 0
B93: Sale Of Pass Book | E93: 0 | G93: 0
B94: Sale Of Loan Form | E94: 0 | G94: 0
B95: Withdrawal Charges | E95: 0 | G95: 0
B96: Commissions (e.g. Commission on Loan Protection Plan (LPP) | E96: 0 | G96: 0
B97: Other Income 1 | E97: 0 | G97: 0
B98: Other Income 2 | E98: 0 | G98: 0
B99: Other Income 3 | E99: 0 | G99: 0
B100: Other Income 4 | E100: 0 | G100: 0
B101: TOTAL | E101: =SUM(E91:F100) -> 0 | G101: =SUM(G91:H100) -> 0
B103: EXPENSES
B105: COST OF FUNDS | E105: CURRENT MONTH | G105: YEAR TO DATE
B106: Interest on Member Savings | E106: 0 | G106: 0
B107: Interest on Other Member Deposits | E107: 0 | G107: 0
B108: Interest on External Loans | E108: 0 | G108: 0
B109: TOTAL | E109: =SUM(E106:F108) -> 0 | G109: =SUM(G106:H108) -> 0
B111: OPERATING EXPENSES
B113: PERSONNEL COST | E113: CURRENT MONTH | G113: YEAR TO DATE
B114: Staff Salaries | E114: 0 | G114: 0
B115: SSNIT contribution, part of CU | E115: 0 | G115: 0
B116: Staff Allowance/ Overtime | E116: 0 | G116: 0
B117: Dressing Allowance | E117: 0 | G117: 0
B118: Cashiers Allowance | E118: 0 | G118: 0
B119: Medical Expenses | E119: 0 | G119: 0
B120: C-CUPP, part of CU | E120: 0 | G120: 0
B121: Other Personnel Cost | E121: 0 | G121: 0
B122: TOTAL | E122: =SUM(E114:F121) -> 0 | G122: =SUM(G114:H121) -> 0 | H122: =SUM(H114:H121) -> 0
...

Sheet BOG specimen BS
A1: Monthly Return on Assets, Liabilities and Own Funds
A2: =CONCATENATE("Institution Name:"," ",NOTES!D7) -> Institution Name: XXXX CO-OPERATIVE CREDIT UNION LTD.
A3: AGGREGATED
A4: Date: | B4: =Reporting!E7 -> 44865
A6: Amount in GH¢ | C6: 39478 | D6: 39479 | E6: 39509 | F6: 39541 | G6: 39572 | H6: 39604 | I6: 39635 | J6: 39667 | K6: 39699 | L6: 39730 | M6: 39762
A7: Item Code | B7: Description | C7: AMOUNT (Gh¢) | D7: AMOUNT (Gh¢) | E7: AMOUNT (Gh¢) | F7: AMOUNT (Gh¢) | G7: AMOUNT (Gh¢) | H7: AMOUNT (Gh¢) | I7: AMOUNT (Gh¢) | J7: AMOUNT (Gh¢) | K7: AMOUNT (Gh¢) | L7: AMOUNT (Gh¢) | M7: AMOUNT (Gh¢) | N7: =Reporting!E7 -> 44865
B8: ASSETS
A9: 10010 | B9: 1) Cash and Short term funds (Total) | N9: =N10+N11+N12+N15 -> 0
A10: 10020 | B10: (a) Cash on Hand | N10: =NOTES!G178 -> 0
A11: 10030 | B11: (b) Balances in current Accounts with banks | N11: =NOTES!G185 -> 0
A12: 10040 | B12: (c) Deposits at banks | N12: =N13+N14 -> 0
A13: 10050 | B13: i) Call funds and term deposits at banks | N13: =SUM(NOTES!G190:H194) -> 0
A14: 10060 | B14: ii) Certificates of Deposits | N14: 0
A15: 10070 | B15: (d) Call and short term deposits with discount houses | N15: =SUM(NOTES!G202:H207) -> 0
A16: 10080 | B16: 2) Loans and Credits (net) - Annex (MSL101) | N16: =N24+N25 -> 0
A17: 10090 | B17: (a) Government
A18: 10100 | B18: (b) Public institutions
A19: 10110 | B19: (c) Public enterprises | N19: =N20+N21 -> 0
A20: 10120 | B20: i) Cocoa Syndicated Loan
A21: 10130 | B21: ii) Others
A22: 10140 | B22: (d) Private enterprises | N22: 0
A23: 10150 | B23: (e) Individuals | N23: =NOTES!G233 -> 0
A24: 10160 | B24: (f) Sub-total | N24: =N17+N18+N19+N22+N23 -> 0
A25: 10170 | B25: (g) Less:Total debt provision | N25: =-NOTES!G234 -> 0
A26: 10180 | B26: 3) Bills (Short-term investments) issued by: | N26: =N27+N32+N39+N43+N44+N45+N49 -> 0
A27: 10190 | B27: (a) Government-Treasury Bills | N27: =SUM(N28+N29+N30+N31) -> 0
A28: 10200 | B28: i) 91 Day | N28: =SUM(NOTES!G195:H197) -> 0
A29: 10210 | B29: ii) 182 Day | N29: =SUM(NOTES!G198:H201) -> 0
A30: 10220 | B30: iii) 1 Year Bond/Stock
A31: 10230 | B31: iv) Others
A32: 10240 | B32: (b) Bank of Ghana bills | N32: =SUM(N33+N34+N35+N36+N37+N38) -> 0
A33: 10250 | B33: i) 28 Day bill
A34: 10260 | B34: ii) 56 Day bill
A35: 10270 | B35: iii) 91 Day bill
A36: 10280 | B36: iv) 182 Day bill
A37: 10290 | B37: v) 1 Year Bond/Stock
A38: 10300 | B38: vi) Others | N38: 0
A39: 10310 | B39: (c) Depository Institutions | N39: =SUM(N40+N41+N42) -> 0
A40: 10320 | B40: i) Commercial Bank
A41: 10330 | B41: ii) Discount House
A42: 10340 | B42: iii) Other Depository | N42: 0
A43: 10350 | B43: (d) Other financial institutions | N43: 0
A44: 10360 | B44: (e) Public institutions
A45: 10370 | B45: (f) Public enterprises | N45: =SUM(N46+N47+N48) -> 0
A46: 10380 | B46: i) Cocoa bills
A47: 10390 | B47: ii) Grains bills
A48: 10400 | B48: iii) Others
A49: 10410 | B49: (g) Private Sector securities with less than 1 year to maturity | N49: =SUM(N50+N51) -> 0
A50: 10420 | B50: i) Bonds
A51: 10430 | B51: ii) Stocks
A52: 10440 | B52: 4) Securities others than shares (long-term investments) issued by: | N52: =N53+N59+N64+N72+N75+N78+N81 -> 0
A53: 10450 | B53: (a) Government | N53: =N54+N55+N56+N57+N58 -> 0
A54: 10460 | B54: i) GGILB
A55: 10470 | B55: ii) 1 year Bonds
A56: 10480 | B56: iii) 2 year Bonds
A57: 10490 | B57: iv) 3 year Bonds
A58: 10500 | B58: v) Others | N58: =NOTES!G216 -> 0
A59: 10510 | B59: (b) Bank of Ghana | N59: =N60+N61+N62+N63 -> 0
A60: 10520 | B60: i) 1 year bond
A61: 10530 | B61: ii) 2 year bond
A62: 10540 | B62: iii) 3 year bond
A63: 10550 | B63: iv)Others
A64: 10560 | B64: (c) Depository institutions | N64: =N65+N68+N69+N70+N71 -> 0
A65: 10570 | B65: i) Commercial bank | N65: =N66+N67 -> 0
A66: 10580 | B66: Bonds
A67: 10590 | B67: Others
A68: 10600 | B68: ii) Rural banks
A69: 10610 | B69: iii) Discount houses
A70: 10620 | B70: iv) Savings and loans companies
A71: 10630 | B71: v) Credit Unions | N71: =SUM(NOTES!G213,NOTES!G208,NOTES!G209) -> 0
A72: 10640 | B72: (d) Other financial institutions | N72: =N73+N74 -> 0
A73: 10650 | B73: i) Bonds
A74: 10660 | B74: ii) Others | N74: 0
A75: 10670 | B75: (e) Public institutions | N75: =N76+N77 -> 0
A76: 10680 | B76: i) Bonds
A77: 10690 | B77: ii) Others
A78: 10700 | B78: (f) Public enterprises | N78: =N79++N80+N81 -> 0
A79: 10710 | B79: i) Bonds
A80: 10720 | B80: ii) Others | N80: =SUM(NOTES!G217:H218) -> 0
A81: 10730 | B81: (g) Private enterprises
A82: 10740 | B82: i) Bonds
A83: 10750 | B83: ii) Others
A84: 10760 | B84: 5) Shares and other Equity (Net) - Annex (MSL102) | N84: =N93-N94 -> 0
A85: 10770 | B85: (a) Depository institutions | N85: =N86+N87+N88+N89 -> 0
A86: 10780 | B86: i) Commercial banks
A87: 10790 | B87: ii) Rural banks
A88: 10800 | B88: iii) Savings and loans companies
A89: 10810 | B89: iv) Credit unions | N89: =SUM(NOTES!G214:H215) -> 0
A90: 10820 | B90: (b) Other financial institutions
A91: 10830 | B91: (c) Public enterprises
A92: 10840 | B92: (d) Private enterprises | N92: 0
A93: 10850 | B93: Sub-total | N93: =N85+N90+N91+N92 -> 0
A94: 10860 | B94: Less:Impairment in value
A95: 10870 | B95: 6) Others Assets - Annex (MSL103) | N95: =NOTES!G246 -> 0
A96: 10880 | B96: 7) Property, Plant & Equipment (Net) | N96: =N105-N106 -> 0
A97: 10890 | B97: (a) Land and premises | N97: =NOTES!G249 -> 0
A98: 10900 | B98: i) Business premises | N98: =NOTES!G250 -> 0
A99: 10910 | B99: ii)Land and Premises for staff and staff amenities | N99: 0
A100: 10920 | B100: (b) Computers | N100: =NOTES!G254 -> 0
A101: 10930 | B101: (c) Furnitures, fixtures and equipment | N101: =NOTES!G253 -> 0
...

Sheet Youth Savings
A1: `
B2: Name of Youth Savings Club
A7: YOUTH SAVINGS PROGRAM FINANCIAL & STATISTICAL REPORT FOR THE MONTH OF | E7: 44743
A9: A. MEMBERSHIP
A11: GENDER | B11: BEGINNING | C11: ADDITIONS | D11: WITHDRAWAL | E11: Total
A12: MALE | B12: 3207 | C12: 6039 | D12: 0 | E12: =(B12+C12)-D12 -> 9246
A13: FEMALE | B13: 14603294 | C13: 26589896 | D13: 0 | E13: =(B13+C13)-D13 -> 41193190
A14: GROUP | B14: 43156555 | C14: 78241826 | D14: 0 | E14: =(B14+C14)-D14 -> 1.2139838e+08
A15: TOTAL | B15: =SUM(B12:B14) -> 57763056 | C15: =SUM(C12:C14) -> 1.0483776e+08 | D15: =SUM(D12:D14) -> 0 | E15: =SUM(E12:E14) -> 1.6260082e+08
A17: B. SAVINGS
A19: GENDER | B19: BEGINNING | C19: ADDITIONS | D19: WITHDRAWAL | E19: Total
A20: MALE | B20: 3207 | C20: 6039 | D20: 0 | E20: =(B20+C20)-D20 -> 9246
A21: FEMALE | B21: 14603294 | C21: 26589896 | D21: 0 | E21: =(B21+C21)-D21 -> 41193190
A22: GROUP | B22: 43156555 | C22: 78241826 | D22: 0 | E22: =(B22+C22)-D22 -> 1.2139838e+08
A23: TOTAL | B23: =SUM(B20:B22) -> 57763056 | C23: =SUM(C20:C22) -> 1.0483776e+08 | D23: =SUM(D20:D22) -> 0 | E23: =SUM(E20:E22) -> 1.6260082e+08
A25: C. INVESTMENTS
A27: TYPE | B27: BEGINNING | C27: ADDITIONS | D27: WITHDRAWAL | E27: Total
A28: Treasury Bills | B28: 3207 | C28: 6039 | D28: 0 | E28: =(B28+C28)-D28 -> 9246
A29: Others | B29: 14603294 | C29: 26589896 | D29: 0 | E29: =(B29+C29)-D29 -> 41193190
A30: Others | B30: 43156555 | C30: 78241826 | D30: 0 | E30: =(B30+C30)-D30 -> 1.2139838e+08
A31: TOTAL | B31: =SUM(B28:B30) -> 57763056 | C31: =SUM(C28:C30) -> 1.0483776e+08 | D31: =SUM(D28:D30) -> 0 | E31: =SUM(E28:E30) -> 1.6260082e+08
A36: Name Manager or Teacher Supervisor | D36: Name of YSP Member / Executive
A39: Signature:................................................... | D39: Signature:..........................................
A45: Data Validation Input Messages: | C45: Chapter | E45: Type of CUs
A46: Please enter it as month/year (for example: 1/2011) | B46: 1 | C46: Accra | E46: Community
A47: Please select the chapter | B47: 2 | C47: Ashanti | E47: Parish
A48: Please enter it in the format dd/mm/yyyy (for example: 01/01/2011) | B48: 3 | C48: Brong-Ahafo | E48: Workplace
A49: Please select the type of your CU | B49: 4 | C49: Central
A50: Please only enter a figure here, if you don't have the figures separted by "females", "males" and "groups" | B50: 5 | C50: Eastern
A51: Please enter a whole number, like 456 for instance | B51: 6 | C51: Northern
A52: Please enter a number, which may be decimal like 456.78 | B52: 7 | C52: Tema
A53: Please enter a number which may be decimal like 456.78. The value may be negative. | B53: 8 | C53: Upper East
B54: 9 | C54: Upper West
B55: 10 | C55: Volta
B56: 11 | C56: Western

Sheet Loans Report
B3: 7. DETAILED BORROWERS AND LOAN INFORMATION
B5: 7a. DETAILED OUTSTANDING LOAN INFORMATION
D7: Gender | G7: Loan Type | L7: Security
C8: Total | D8: Females | E8: Males | F8: Groups | G8: Business | H8: Auto | I8: Housing | J8: School Fees | K8: Other | L8: Member Guar/Lien on Sav | M8: Fin Invest | N8: Landed Prop | O8: Auto | P8: Other
B9: Number of Borrowers from previous month | C9: =SUM(D9:F9) -> 0 | D9: 0 | E9: 0 | F9: 0 | G9: 0 | H9: 0 | I9: 0 | J9: 0 | K9: 0 | L9: 0 | M9: 0 | N9: 0 | O9: 0 | P9: 0
B10: Additional number of new loans given during reporting month | C10: =SUM(D10:F10) -> 0
B11: Reduction in number of loans by completing their payments during reporting month | C11: =SUM(D11:F11) -> 0
B12: Net Increase/(Decrease) of Borrowers during reporting month | C12: =+C10-C11 -> 0 | D12: =+D10-D11 -> 0 | E12: =+E10-E11 -> 0 | F12: =+F10-F11 -> 0 | G12: =+G10-G11 -> 0 | H12: =+H10-H11 -> 0 | I12: =+I10-I11 -> 0 | J12: =+J10-J11 -> 0 | ... P12: =+P10-P11 -> 0
B13: New total Debitors at the end of reporting month | C13: =SUM(D13:F13) -> 0 | D13: =+D9+D12 -> 0 | E13: =+E9+E12 -> 0 | F13: =+F9+F12 -> 0 | G13: =+G9+G12 -> 0 | H13: =+H9+H12 -> 0 | I13: =+I9+I12 -> 0 | J13: =+J9+J12 -> 0 | K13: =+K9+K12 -> 0 | ... P13: =+P9+P12 -> 0
B15: Amount of outstanding loans from previous month | C15: =SUM(D15:F15) -> 0 | D15: 0 | E15: 0 | F15: 0 | G15: 0 | H15: 0 | I15: 0 | J15: 0 | K15: 0 | L15: 0 | M15: 0 | N15: 0 | O15: 0 | P15: 0
B16: Additional amount of new loans given during reporting month | C16: =SUM(D16:F16) -> 0
B17: Amount of loan payments during reporting month | C17: =SUM(D17:F17) -> 0
B18: Net Increase/(Decrease) of outstanding loans during reporting month | C18: =+C16-C17 -> 0 | D18: =+D16-D17 -> 0 | E18: =+E16-E17 -> 0 | F18: =+F16-F17 -> 0 | G18: =+G16-G17 -> 0 | H18: =+H16-H17 -> 0 | I18: =+I16-I17 -> 0 | J18: =+J16-J17 -> 0 | ... P18: =+P16-P17 -> 0
B19: New outstanding loans at the end of reporting month | C19: =SUM(D19:F19) -> 0 | D19: =+D15+D18 -> 0 | E19: =+E15+E18 -> 0 | F19: =+F15+F18 -> 0 | G19: =+G15+G18 -> 0 | H19: =+H15+H18 -> 0 | I19: =+I15+I18 -> 0 | J19: =+J15+J18 -> 0 | K19: =+K15+K18 -> 0 | ... P19: =+P15+P18 -> 0
B21: 7b. DETAILED LOAN DELINQUENCY INFORMATION/ AGEING SCHEDULE & PROVISIONING
D23: Gender | G23: Loan Type | L23: Security
B24: Number of borrowers with delay in payment of … days | C24: Total | D24: Females | E24: Males | F24: Groups | G24: Business | H24: Auto | I24: Housing | J24: School Fees | K24: Other | L24: Member Guar/Lien on Sav | M24: Fin Invest | N24: Landed Prop | O24: Auto | P24: Other
B25: Current Loans | C25: =SUM(D25:F25) -> 0
B26: 1 - 30 days | C26: =SUM(D26:F26) -> 0
B27: 31 - 60 days (1 month - 2 months) | C27: =SUM(D27:F27) -> 0
B28: 61 - 90 days (2 month - 3 months) | C28: =SUM(D28:F28) -> 0
B29: 91 - 180 days (4 month - 6 months) | C29: =SUM(D29:F29) -> 0
B30: 181 - 270 days (7 month - 9 months) | C30: =SUM(D30:F30) -> 0
B31: 271 - 365 days (10 month - 12 months) | C31: =SUM(D31:F31) -> 0
B32: Number of delinquent borrowers during reporting month | C32: =SUM(D32:F32) -> 0 | D32: =+SUM(D25:D31) -> 0 | E32: =+SUM(E25:E31) -> 0 | F32: =+SUM(F25:F31) -> 0 | G32: =+SUM(G25:G31) -> 0 | H32: =+SUM(H25:H31) -> 0 | I32: =+SUM(I25:I31) -> 0 | J32: =+SUM(J25:J31) -> 0 | K32: =+SUM(K25:K31) -> 0 | ... P32: =+SUM(P25:P31) -> 0
B33: over 366 days (over 12 months) | C33: =SUM(D33:F33) -> 0
B34: Number of delinquent borrowers during reporting month (including set aside) | C34: =SUM(D34:F34) -> 0 | D34: =+D32+D33 -> 0 | E34: =+E32+E33 -> 0 | F34: =+F32+F33 -> 0 | G34: =+G32+G33 -> 0 | H34: =+H32+H33 -> 0 | I34: =+I32+I33 -> 0 | J34: =+J32+J33 -> 0 | K34: =+K32+K33 -> 0 | ... P34: =+P32+P33 -> 0
B35: Total Number of Loans at end of reporting month (including set aside) | C35: =SUM(D35:F35) -> 0 | D35: =D25+D34 -> 0 | E35: =E25+E34 -> 0 | F35: =F25+F34 -> 0 | G35: =G25+G34 -> 0 | H35: =H25+H34 -> 0 | I35: =I25+I34 -> 0 | J35: =J25+J34 -> 0 | K35: =K25+K34 -> 0 | ... P35: =P25+P34 -> 0
D37: Gender | G37: Loan Type | L37: Security
B38: Amount of outstanding loans with delay in payment of … days (Portfolio at risk amount) | C38: Total | D38: Females | E38: Males | F38: Groups | G38: Business | H38: Auto | I38: Housing | J38: School Fees | K38: Other | L38: Member Guar/Lien on Sav | M38: Fin Invest | N38: Landed Prop | O38: Auto | P38: Other
B39: Current Loans | C39: =SUM(D39:F39) -> 0
B40: 1 - 30 days | C40: =SUM(D40:F40) -> 0
B41: 31 - 60 days (1 month - 2 months) | C41: =SUM(D41:F41) -> 0
B42: 61 - 90 days (2 month - 3 months) | C42: =SUM(D42:F42) -> 0
B43: 91 - 180 days (4 month - 6 months) | C43: =SUM(D43:F43) -> 0
B44: 181 - 270 days (7 month - 9 months) | C44: =SUM(D44:F44) -> 0
B45: 271 - 365 days (10 month - 12 months) | C45: =SUM(D45:F45) -> 0
B46: Amount of delinquent loans during reporting month | C46: =SUM(D46:F46) -> 0 | D46: =+SUM(D39:D45) -> 0 | E46: =+SUM(E39:E45) -> 0 | F46: =+SUM(F39:F45) -> 0 | G46: =+SUM(G39:G45) -> 0 | H46: =+SUM(H39:H45) -> 0 | I46: =+SUM(I39:I45) -> 0 | J46: =+SUM(J39:J45) -> 0 | K46: =+SUM(K39:K45) -> 0 | ... P46: =+SUM(P39:P45) -> 0
B47: over 366 days (over 12 months) | C47: =SUM(D47:F47) -> 0
B48: Amount of delinquent loans during reporting month (including set aside) | C48: =SUM(D48:F48) -> 0 | D48: =+D46+D47 -> 0 | E48: =+E46+E47 -> 0 | F48: =+F46+F47 -> 0 | G48: =+G46+G47 -> 0 | H48: =+H46+H47 -> 0 | I48: =+I46+I47 -> 0 | J48: =+J46+J47 -> 0 | K48: =+K46+K47 -> 0 | ... P48: =+P46+P47 -> 0
B49: Total Amount of Loans at end of reporting month (including set aside) | C49: =SUM(D49:F49) -> 0 | D49: =D39+D48 -> 0 | E49: =E39+E48 -> 0 | F49: =F39+F48 -> 0 | G49: =G39+G48 -> 0 | H49: =H39+H48 -> 0 | I49: =I39+I48 -> 0 | J49: =J39+J48 -> 0 | K49: =K39+K48 -> 0 | ... P49: =P39+P48 -> 0
B51: Provisioning for Loan Losses | C51: Total | D51: Females | E51: Males | F51: Groups | G51: Loan Loss Prov Rates | H51: Loan Loss Prov Amount | I51: Previous Prov Amount | J51: increase in Loan Loss Prov
B52: Current Loans | C52: =SUM(D52:F52) -> 0 | D52: =D39 -> 0 | E52: =E39 -> 0 | F52: =F39 -> 0 | G52: 0.01 | H52: =C52*G52 -> 0 | J52: =H52-I52 -> 0
B53: 1 - 30 days | C53: =SUM(D53:F53) -> 0 | D53: =D40 -> 0 | E53: =E40 -> 0 | F53: =F40 -> 0 | G53: 0.1 | H53: =C53*G53 -> 0 | J53: =H53-I53 -> 0
B54: 31 - 60 days (1 month - 2 months) | C54: =SUM(D54:F54) -> 0 | D54: =D41 -> 0 | E54: =E41 -> 0 | F54: =F41 -> 0 | G54: 0.1 | H54: =C54*G54 -> 0 | J54: =H54-I54 -> 0
B55: 61 - 90 days (2 month - 3 months) | C55: =SUM(D55:F55) -> 0 | D55: =D42 -> 0 | E55: =E42 -> 0 | F55: =F42 -> 0 | G55: 0.1 | H55: =C55*G55 -> 0 | J55: =H55-I55 -> 0
B56: 91 - 180 days (4 month - 6 months) | C56: =SUM(D56:F56) -> 0 | D56: =D43 -> 0 | E56: =E43 -> 0 | F56: =F43 -> 0 | G56: 0.3 | H56: =C56*G56 -> 0 | J56: =H56-I56 -> 0
B57: 181 - 270 days (7 month - 9 months) | C57: =SUM(D57:F57) -> 0 | D57: =D44 -> 0 | E57: =E44 -> 0 | F57: =F44 -> 0 | G57: 0.6 | H57: =C57*G57 -> 0 | J57: =H57-I57 -> 0
B58: 271 - 365 days (10 month - 12 months) | C58: =SUM(D58:F58) -> 0 | D58: =D45 -> 0 | E58: =E45 -> 0 | F58: =F45 -> 0 | G58: 1 | H58: =C58*G58 -> 0 | J58: =H58-I58 -> 0
B59: Amount of delinquent loans during reporting month | C59: =SUM(D59:F59) -> 0 | D59: =+SUM(D52:D58) -> 0 | E59: =+SUM(E53:E58) -> 0 | F59: =+SUM(F53:F58) -> 0 | H59: =+SUM(H53:H58) -> 0 | I59: =+SUM(I53:I58) -> 0 | J59: =H59-I59 -> 0
B60: over 366 days (over 12 months) | C60: =SUM(D60:F60) -> 0 | D60: =D47 -> 0 | E60: =E47 -> 0 | F60: =F47 -> 0 | G60: 1 | H60: =C60*G60 -> 0 | J60: =H60-I60 -> 0
B61: Amount of delinquent loans during reporting month (including set aside) | C61: =SUM(D61:F61) -> 0 | D61: =+D59+D60 -> 0 | E61: =+E59+E60 -> 0 | F61: =+F59+F60 -> 0 | H61: =+H59+H60 -> 0 | I61: =+I59+I60 -> 0 | J61: =H61-I61 -> 0
B62: Total Amount of Loans at end of reporting month (including set aside) | C62: =SUM(D62:F62) -> 0 | D62: =D52+D61 -> 0 | E62: =E52+E61 -> 0 | F62: =F52+F61 -> 0 | H62: =H52+H61 -> 0 | I62: =I52+I61 -> 0 | J62: =H62-I62 -> 0
D64: Gender | G64: Loan Type | L64: Security
B65: Defaulted/delinquent amount with delay in payment of … days (Portfolio in arrears amount) | C65: Total | D65: Females | E65: Males | F65: Groups | G65: Business | H65: Auto | I65: Housing | J65: School Fees | K65: Other | L65: Member Guar/Lien on Sav | M65: Fin Invest | N65: Landed Prop | O65: Auto | P65: Other
B66: 1 - 30 days | C66: =SUM(D66:F66) -> 0
B67: 31 - 60 days (1 month - 2 months) | C67: =SUM(D67:F67) -> 0
B68: 61 - 90 days (2 month - 3 months) | C68: =SUM(D68:F68) -> 0
B69: 91 - 180 days (4 month - 6 months) | C69: =SUM(D69:F69) -> 0
B70: 181 - 270 days (7 month - 9 months) | C70: =SUM(D70:F70) -> 0
B71: 271 - 365 days (10 month - 12 months) | C71: =SUM(D71:F71) -> 0
B72: Amount of delinquent loans during reporting month | C72: =SUM(D72:F72) -> 0 | D72: =+SUM(D65:D71) -> 0 | E72: =+SUM(E65:E71) -> 0 | F72: =+SUM(F65:F71) -> 0 | G72: =+SUM(G65:G71) -> 0 | H72: =+SUM(H65:H71) -> 0 | I72: =+SUM(I65:I71) -> 0 | J72: =+SUM(J65:J71) -> 0 | K72: =+SUM(K65:K71) -> 0 | ... P72: =+SUM(P65:P71) -> 0
B73: over 366 days (over 12 months) | C73: =SUM(D73:F73) -> 0
B74: Amount of delinquent loans during reporting month (including set aside) | C74: =SUM(D74:F74) -> 0 | D74: =+D72+D73 -> 0 | E74: =+E72+E73 -> 0 | F74: =+F72+F73 -> 0 | G74: =+G72+G73 -> 0 | H74: =+H72+H73 -> 0 | I74: =+I72+I73 -> 0 | J74: =+J72+J73 -> 0 | K74: =+K72+K73 -> 0 | ... P74: =+P72+P73 -> 0
B77: 7c. LOAN CONCENTRATION
B79: By Amount/Size: | C79: DISBURSED (YTD) | D79: OUTSTANDING
C80: GHS | D80: GHS
B81: Average loan size
B83: Twenty Largest Loans
C84: DISBURSED (YTD) | D84: OUTSTANDING
C85: GHS | D85: GHS
A86: 1
A87: 2
A88: 3
A89: 4
A90: 5
A91: 6
A92: 7
A93: 8
A94: 9
A95: 10
A96: 11
A97: 12
... A105: 20
B106: Total | C106: =SUM(C86:C105) -> 0 | D106: =SUM(D86:D105) -> 0
B107: Total Loans as at reporting date
B108: Twenty Largest Loans as percentage of Total Loans
B112: By Sector (Number and Amount, Performing/Non-Performing) | C112: TOTAL | E112: PERFORMING | G112: NON-PERFORMING
C113: Number | D113: GHS | E113: Number | F113: GHS | G113: Number | H113: GHS
B114: Commerce/Trading/Finance
B115: Consumer Finance
B116: Education/Human Capital development
B117: Construction/Housing
B118: Funeral
B119: Agriculture/Forestry/Fishing
B120: Manufacturing
B121: Transport/Storage/Communication
B122: Other Services
B123: Electricity/Gas/Water
B124: Mining & Quarrying
...

Sheet Liquidity Report
C2: =NOTES!D7 -> XXXX CO-OPERATIVE CREDIT UNION LTD.
E5: Credit Union ID: | F5: =NOTES!F5 -> 0
B7: FINANCIAL & STATISTICAL REPORT FOR THE MONTH OF | F7: 42734
A9: A. | B9: LIQUIDITY REPORT
B10: Day | C10: 1 | D10: 2 | E10: 3 | F10: 4 | G10: 5 | H10: 6 | I10: 7 | J10: 8 | K10: 9 | L10: 10 | M10: 11 | N10: 12 | O10: 13 | P10: 14 | Q10: 15 | R10: 16 | S10: 17 | T10: 18 | U10: 19 | V10: 20 | W10: 21 | X10: 22 | Y10: 23 | Z10: 24 | AA10: 25 | AB10: 26 | AC10: 27 | AD10: 28 | AE10: 29 | AF10: 30 | AG10: 31 | AH10: Ave
B11: DEPOSIT LIABILITIES | C11: GHS | D11: GHS | E11: GHS | F11: GHS | G11: GHS | H11: GHS | I11: GHS | J11: GHS | K11: GHS | L11: GHS | M11: GHS | N11: GHS | O11: GHS | P11: GHS | Q11: GHS | R11: GHS | S11: GHS | T11: GHS | U11: GHS | V11: GHS | W11: GHS | X11: GHS | Y11: GHS | Z11: GHS | AA11: GHS | AB11: GHS | AC11: GHS | AD11: GHS | AE11: GHS | AF11: GHS | AG11: GHS | AH11: GHS
B12: Regular Savings | AH12: =AVERAGE(C12:AG12) -> #DIV/0!
B13: Mobile Banking (Savings) | AH13: =AVERAGE(C13:AG13) -> #DIV/0!
B14: Call Deposits | AH14: =AVERAGE(C14:AG14) -> #DIV/0!
B15: Time Deposits | AH15: =AVERAGE(C15:AG15) -> #DIV/0!
B16: Other | AH16: =AVERAGE(C16:AG16) -> #DIV/0!
B17: Total | C17: =SUM(C12:C15) -> 0 | D17: =SUM(D12:D15) -> 0 | E17: =SUM(E12:E15) -> 0 | F17: =SUM(F12:F15) -> 0 | G17: =SUM(G12:G15) -> 0 | H17: =SUM(H12:H15) -> 0 | I17: =SUM(I12:I15) -> 0 | J17: =SUM(J12:J15) -> 0 | ... AH17: =SUM(AH12:AH15) -> #DIV/0!
B18: LIQUID ASSETS
B19: Cash | AH19: =AVERAGE(C19:AF19) -> #DIV/0!
B20: Bank Current A/c | AH20: =AVERAGE(C20:AF20) -> #DIV/0!
B21: Total Prim res | C21: =C19+C20 -> 0 | D21: =D19+D20 -> 0 | E21: =E19+E20 -> 0 | F21: =F19+F20 -> 0 | G21: =G19+G20 -> 0 | H21: =H19+H20 -> 0 | I21: =I19+I20 -> 0 | J21: =J19+J20 -> 0 | ... AH21: =AH19+AH20 -> #DIV/0!
B22: Bank Savings A/c | AH22: =AVERAGE(C22:AF22) -> #DIV/0!
B23: Bank Time Deposits | AH23: =AVERAGE(C23:AF23) -> #DIV/0!
B24: CUA CFF Savings Deposit | AH24: =AVERAGE(C24:AF24) -> #DIV/0!
B25: CUA CFF Time Deposit | AH25: =AVERAGE(C25:AF25) -> #DIV/0!
B26: CUFix Investments | AH26: =AVERAGE(C26:AF26) -> #DIV/0!
B27: Treasury Bills - GoG | AH27: =AVERAGE(C27:AF27) -> #DIV/0!
B28: BoG Bills | AH28: =AVERAGE(C28:AF28) -> #DIV/0!
B29: Bonds - GoG | AH29: =AVERAGE(C29:AF29) -> #DIV/0!
B30: Bonds - BoG | AH30: =AVERAGE(C30:AF30) -> #DIV/0!
B31: Other Liquid Investments | AH31: =AVERAGE(C31:AF31) -> #DIV/0!
B32: Total Liquid Investments | C32: =SUM(C22:C31) -> 0 | D32: =SUM(D22:D31) -> 0 | E32: =SUM(E22:E31) -> 0 | F32: =SUM(F22:F31) -> 0 | G32: =SUM(G22:G31) -> 0 | H32: =SUM(H22:H31) -> 0 | I32: =SUM(I22:I31) -> 0 | J32: =SUM(J22:J31) -> 0 | ... AG32: =SUM(AG22:AG31) -> 0 | AH32: =AVERAGE(C32:AF32) -> 0
B33: TOTAL LIQUID ASSETS | C33: =C21+C32 -> 0 | D33: =D21+D32 -> 0 | E33: =E21+E32 -> 0 | F33: =F21+F32 -> 0 | G33: =G21+G32 -> 0 | H33: =H21+H32 -> 0 | I33: =I21+I32 -> 0 | J33: =J21+J32 -> 0 | ... AG33: =AG21+AG32 -> 0 | AH33: =AVERAGE(C33:AF33) -> 0
B35: Loans Outstanding | AH35: =AVERAGE(C35:AF35) -> #DIV/0!
B36: Total Assets | AH36: =AVERAGE(C36:AF36) -> #DIV/0!
B37: Req Liq -cash(3%) | C37: =C36*2% -> 0 | D37: =D36*2% -> 0 | E37: =E36*2% -> 0 | F37: =F36*2% -> 0 | G37: =G36*2% -> 0 | H37: =H36*2% -> 0 | I37: =I36*2% -> 0 | J37: =J36*2% -> 0 | ... AH37: =AH36*2% -> #DIV/0!
B38: Req Liq -inv(17%) | C38: =C36*18% -> 0 | D38: =D36*18% -> 0 | E38: =E36*18% -> 0 | F38: =F36*18% -> 0 | G38: =G36*18% -> 0 | H38: =H36*18% -> 0 | I38: =I36*18% -> 0 | J38: =J36*18% -> 0 | ... AH38: =AH36*18% -> #DIV/0!
B39: Req Total Liq Assets (20%) | C39: =C37+C38 -> 0 | D39: =D37+D38 -> 0 | E39: =E37+E38 -> 0 | F39: =F37+F38 -> 0 | G39: =G37+G38 -> 0 | H39: =H37+H38 -> 0 | I39: =I37+I38 -> 0 | J39: =J37+J38 -> 0 | ... AH39: =AH37+AH38 -> #DIV/0!
B40: Excess/(Deficit) | C40: =C33-C38 -> 0 | D40: =D33-D38 -> 0 | E40: =E33-E38 -> 0 | F40: =F33-F38 -> 0 | G40: =G33-G38 -> 0 | H40: =H33-H38 -> 0 | I40: =I33-I38 -> 0 | J40: =J33-J38 -> 0 | ... AH40: =AH33-AH38 -> #DIV/0!
B41: Total Liquid Assets/Deposits | C41: =C33/C12 -> #DIV/0! | D41: =D33/D12 -> #DIV/0! | E41: =E33/E12 -> #DIV/0! | F41: =F33/F12 -> #DIV/0! | G41: =G33/G12 -> #DIV/0! | H41: =H33/H12 -> #DIV/0! | I41: =I33/I12 -> #DIV/0! | J41: =J33/J12 -> #DIV/0! | ... AH41: =AH33/AH12 -> #DIV/0!
B42: Total Liquid Assets/Total Assets | C42: =C33/C36 -> #DIV/0! | D42: =D33/D36 -> #DIV/0! | E42: =E33/E36 -> #DIV/0! | F42: =F33/F36 -> #DIV/0! | G42: =G33/G36 -> #DIV/0! | H42: =H33/H36 -> #DIV/0! | I42: =I33/I36 -> #DIV/0! | J42: =J33/J36 -> #DIV/0! | ... AH42: =AH33/AH36 -> #DIV/0!
B43: Cash&Bank/Total Assets | C43: =C21/C36 -> #DIV/0! | D43: =D21/D36 -> #DIV/0! | E43: =E21/E36 -> #DIV/0! | F43: =F21/F36 -> #DIV/0! | G43: =G21/G36 -> #DIV/0! | H43: =H21/H36 -> #DIV/0! | I43: =I21/I36 -> #DIV/0! | J43: =J21/J36 -> #DIV/0! | ... AH43: =AH21/AH36 -> #DIV/0!
A46: B. | B46: CUA LIFE SAVINGS PLAN: | AE46: CUMULATIVE | AG46: CURRENT PERIOD
AE47: Number | AF47: GHS | AG47: Number | AH47: GHS
B48: Number of Savings Accounts covered
B49: Amount of Savings covered (GHS)

Sheet Liquidity Gap Table
C2: =NOTES!D7 -> XXXX CO-OPERATIVE CREDIT UNION LTD.
E5: Credit Union ID: | F5: =NOTES!F5 -> 0
B7: FINANCIAL & STATISTICAL REPORT FOR THE MONTH OF | F7: 43921
B8: Liquidity Risk Gap Table
B9: Date of Balance Sheet: 31 Mar 2020
C11: Up to 7 days | D11: 7days-1 month | E11: 2 months | F11: 3 months | G11: 4 months | H11: 5 months | I11: 6 months | J11: 7 months | K11: 8 months | L11: 9 months | M11: 10 months | N11: 11 months | O11: 12 months | P11: 13–18 months | Q11: 19–24 months | R11: 2–5 years | S11: >5 years | T11: No Maturity | U11: Total
B12: Assets
B13: Cash on hand | C13: 40000 | U13: =SUM(C13:T13) -> 40000
B14: Balances in current accounts with bank/Fin Inst | U14: =SUM(C14:T14) -> 0
B15: Balances in savings account with banks/Fin inst | C15: 6000000 | U15: =SUM(C15:T15) -> 6000000
B16: Money on call with banks/fin inst | U16: =SUM(C16:T16) -> 0
B17: Placement with banks/fin inst/Time Deposits | D17: 3000000 | E17: 3000000 | F17: 3000000 | U17: =SUM(C17:T17) -> 9000000
B18: GoG /BOG Securities | U18: =SUM(C18:T18) -> 0
B19: Loans and Advances (principal, net) 1 | D19: 12642500 | E19: 12642500 | F19: 12642500 | G19: 12642500 | H19: 12642500 | I19: 12642500 | J19: 12642500 | K19: 12642500 | L19: 12642500 | M19: 12642500 | N19: 12642500 | O19: 12642500 | U19: =SUM(C19:T19) -> 151710000
B20: Other Assets 2 | D20: 1250000 | U20: =SUM(C20:T20) -> 1250000
B21: Property, Plant and Equipment (net) | T21: 4000000 | U21: =SUM(C21:T21) -> 4000000
B22: Total Assets | C22: =SUM(C13:C21) -> 6040000 | D22: =SUM(D13:D21) -> 16892500 | E22: =SUM(E13:E21) -> 15642500 | F22: =SUM(F13:F21) -> 15642500 | G22: =SUM(G13:G21) -> 12642500 | H22: =SUM(H13:H21) -> 12642500 | I22: =SUM(I13:I21) -> 12642500 | J22: =SUM(J13:J21) -> 12642500 | ... U22: =SUM(U13:U21) -> 172000000
B24: Liabilities
B25: Savings deposits | C25: 100000 | R25: 900000 | U25: =SUM(C25:T25) -> 1000000
B26: Time deposits | F26: 250000 | I26: 250000 | U26: =SUM(C26:T26) -> 500000
B27: Borrowings (principal) | C27: 300000 | D27: 3000000 | E27: 4000000 | F27: 700000 | G27: 265000 | H27: 4000000 | I27: 2000000 | J27: 1500000 | K27: 1750000 | L27: 2834000 | M27: 1000000 | N27: 151000 | O27: 15000000 | P27: 25000000 | Q27: 32000000 | R27: 35000000 | U27: =SUM(C27:T27) -> 128500000
B28: Interest payable | C28: 176701 | D28: 1000000 | E28: 1039360 | F28: 343217 | G28: 470697 | H28: 490267 | I28: 152745 | J28: 161598 | K28: 380486 | L28: 81716 | M28: 96842 | N28: 412215 | O28: 206101 | P28: 1200303 | Q28: 1200303 | R28: 7200000 | U28: =SUM(C28:T28) -> 14612551
B29: Other liabilities 3 | D29: 4000000 | U29: =SUM(C29:T29) -> 4000000
B30: Total Liabilities | C30: =SUM(C25:C29) -> 576701 | D30: =SUM(D25:D29) -> 8000000 | E30: =SUM(E25:E29) -> 5039360 | F30: =SUM(F25:F29) -> 1293217 | G30: =SUM(G25:G29) -> 735697 | H30: =SUM(H25:H29) -> 4490267 | I30: =SUM(I25:I29) -> 2402745 | J30: =SUM(J25:J29) -> 1661598 | ... U30: =SUM(U25:U29) -> 148612551
B31: Total Equity | T31: 38000000 | U31: =SUM(C31:T31) -> 38000000
B32: Total Liabilities & Equity | C32: =C30+C31 -> 576701 | D32: =D30+D31 -> 8000000 | E32: =E30+E31 -> 5039360 | F32: =F30+F31 -> 1293217 | G32: =G30+G31 -> 735697 | H32: =H30+H31 -> 4490267 | I32: =I30+I31 -> 2402745 | J32: =J30+J31 -> 1661598 | ... U32: =U30+U31 -> 186612551
B34: Asset – (Total Liability + Equity) Gap 4 | C34: =C22-C32 -> 5463299 | D34: =D22-D32 -> 8892500 | E34: =E22-E32 -> 10603140 | F34: =F22-F32 -> 14349283 | G34: =G22-G32 -> 11906803 | H34: =H22-H32 -> 8152233 | I34: =I22-I32 -> 10239755 | J34: =J22-J32 -> 10980902 | ... U34: =U22-U32 -> -14612551
B35: Cumulative Gap | C35: =C34 -> 5463299 | D35: =D34+C35 -> 14355799 | E35: =E34+D35 -> 24958939 | F35: =F34+E35 -> 39308222 | G35: =G34+F35 -> 51215025 | H35: =H34+G35 -> 59367258 | I35: =I34+H35 -> 69607013 | J35: =J34+I35 -> 80587915 | K35: =K34+J35 -> 91099929 | ... T35: =T34+S35 -> -14612551 | U35: =T35 -> -14612551
B36: Gap % | C36: =C34/C32 -> 9.4733649 | D36: =D34/D32 -> 1.1115625 | E36: =E34/E32 -> 2.1040648 | F36: =F34/F32 -> 11.095804 | G36: =G34/G32 -> 16.184384 | H36: =H34/H32 -> 1.8155341 | I36: =I34/I32 -> 4.2616903 | J36: =J34/J32 -> 6.6086394 | ... U36: =U34/U32 -> -0.078304224
B37: Notes:
B38: 1. Shows the client loan portfolio (principal) maturing in each time band
B39: 2. Other assets include specific items as may be relevant (e.g. accounts receivable) .
B40: 2. Other liabilities include specific items as may be relevant (e.g. accounts payable such as utilities) .
B41: 4. Total interest payable up to maturity on contracted liabilites may be included in the relevant time bands in which case the total gap may not be zero since the balance sheet does not normally include amounts that are not yet due. In such situation total assets may not equal total liabilities as expected.

Sheet Market Conduct Report
C2: =Reporting!B2 -> 0
E5: Credit Union ID: | F5: =Reporting!E5 -> 0
B7: FINANCIAL & STATISTICAL REPORT FOR THE MONTH OF | F7: =Reporting!E7 -> 44865
B8: Market Conduct Reporting
B9: Date of Balance Sheet as at : | C9: =F7 -> 44865
A12: A. | B12: Interest Rates (by product) | F12: % (pm/pa)
A13: 1 | B13: Savings
A14: 2 | B14: Loans
A16: B. | B16: Complaints Handling Reporting
A17: 1 | B17: Complaints Management System/Register in place during reporting period? (Y/N)
A18: 2 | B18: Cumulative number of complaints outstanding at beginning of reporting period | F18: 10
A19: 3 | B19: Number of new complaints received during reporting period | F19: 5
A20: 4 | B20: Number of new complaints resolved during reporting period | F20: -6
A21: 5 | B21: Cumulative number of complaints outstanding at end of reporting period* | F21: =F18+F19+F20 -> 9
A25: * | B25: Analysis of Outstanding Complaints Details
A26: 1 | B26: Savings account balance
A27: 2 | B27: Savings deposit not credited
A28: 3 | B28: Savings withdrawal delays
A29: 4 | B29: Savings interest rates
A30: 5 | B30: Loan account balance
A31: 6 | B31: Loan approval and disbursement delays
A32: 7 | B32: Loan interest rates
A33: 8 | B33: Dividend payment
A34: 9 | B34: Fraud
A35: 10 | B35: Other
B36: Total | F36: =SUM(F26:F35) -> 0

Sheet Age Distribution of Members
C2: =NOTES!F5 -> 0
C5: Credit Union ID: | F5: =Reporting!E5 -> 0
D7: =Reporting!E7 -> 44865
B8: FINANCIAL & STATISTICAL REPORT FOR THE MONTH OF
B9: Member Distribution by Age as at 31st December 2021
B11: Age Distribution: | C11: Number of Members | D11: Total Savings | E11: Total Shares | F11: Loan Outstanding
B12: Less than 18 Years
B13: 18 to 35 Years
B14: 36 to 60 Years
B15: Above 60 Years
B16: Totals | C16: =SUM(C13:C15) -> 0 | D16: =SUM(D13:D15) -> 0 | E16: =SUM(E13:E15) -> 0 | F16: =SUM(F13:F15) -> 0 | G16: =SUM(G13:G15) -> 0 | H16: =SUM(H13:H15) -> 0 | I16: =SUM(I13:I15) -> 0
